pycanape/__init__.py
pycanape/calibration_object.py
pycanape/canape.py
pycanape/config.py
pycanape/daq.py
pycanape/ecu_task.py
pycanape/module.py
pycanape/py.typed
pycanape/recorder.py
pycanape/script.py
pycanape/utils.py
pycanape/cnp_api/__init__.py
pycanape/cnp_api/cnp_class.py
pycanape/cnp_api/cnp_constants.py
pycanape/cnp_api/cnp_prototype.py
pycanape-0.8.1.dist-info/licenses/LICENSE.txt
pycanape-0.8.1.dist-info/METADATA
pycanape-0.8.1.dist-info/WHEEL
pycanape-0.8.1.dist-info/top_level.txt
pycanape-0.8.1.dist-info/RECORD
