Metadata-Version: 2.4
Name: pyCANape
Version: 0.8.1
Summary: Pythonic wrapper around the VECTOR CANape API
Author-email: Artur Drogunow <artur.drogunow@zf.com>
License-Expression: MIT
Project-URL: Documentation, https://pycanape.readthedocs.io
Project-URL: Issues, https://github.com/zariiii9003/pycanape/issues
Project-URL: Source, https://github.com/zariiii9003/pycanape
Project-URL: Homepage, https://github.com/zariiii9003/pycanape
Keywords: CANape,Measurement,Calibration,automotive
Classifier: Programming Language :: Python
Classifier: Programming Language :: Python :: 3
Requires-Python: >=3.9
License-File: LICENSE.txt
Requires-Dist: psutil
Requires-Dist: numpy>=1.21
Requires-Dist: packaging
Requires-Dist: typing-extensions; python_version < "3.10"
Provides-Extra: dev
Requires-Dist: pytest; extra == "dev"
Requires-Dist: pytest-cov; extra == "dev"
Requires-Dist: python-can==4.*; extra == "dev"
Requires-Dist: ruff==0.12.5; extra == "dev"
Requires-Dist: mypy==1.17.*; extra == "dev"
Provides-Extra: doc
Requires-Dist: furo; extra == "doc"
Requires-Dist: sphinx==8.*; extra == "doc"
Requires-Dist: sphinx-copybutton; extra == "doc"
Dynamic: license-file
